qiskit_gridsynth_plugin/__init__.py
qiskit_gridsynth_plugin/decompose.py
qiskit_gridsynth_plugin/lib/gridsynth_linux
qiskit_gridsynth_plugin/lib/gridsynth_mac
qiskit_gridsynth_plugin/lib/gridsynth_windows.exe
qiskit_gridsynth_plugin-0.0.8.dist-info/METADATA
qiskit_gridsynth_plugin-0.0.8.dist-info/WHEEL
qiskit_gridsynth_plugin-0.0.8.dist-info/top_level.txt
qiskit_gridsynth_plugin-0.0.8.dist-info/RECORD
