Metadata-Version: 2.1
Name: qiskit_gridsynth_plugin
Version: 0.0.8
Summary: A small package for integrating gridsynth angle decomposition into qiskit.
Author-email: Abtin Molavi <amolavi@wisc.edu>
Keywords: qiskit,quantum circuit,quantum computing,quantum,fault tolerant quantum computing
Classifier: Intended Audience :: Developers
Classifier: Intended Audience :: Science/Research
Classifier: License :: OSI Approved :: GNU General Public License v3 (GPLv3)
Classifier: Operating System :: MacOS
Classifier: Operating System :: Microsoft :: Windows
Classifier: Operating System :: POSIX :: Linux
Classifier: Programming Language :: Python :: 3 :: Only
Classifier: Programming Language :: Python :: 3.8
Classifier: Programming Language :: Python :: 3.9
Classifier: Programming Language :: Python :: 3.10
Classifier: Programming Language :: Python :: 3.11
Classifier: Programming Language :: Python :: 3.12
Classifier: Topic :: Scientific/Engineering
Requires-Python: >=3.8
Requires-Dist: qiskit >=1.0
